tests/__init__.py
tests/tests_topsis.py
topsis/Sannidhya_102103348.py
topsis/__init__.py
Sannidhya_102103348-0.2.0.dist-info/METADATA
Sannidhya_102103348-0.2.0.dist-info/WHEEL
Sannidhya_102103348-0.2.0.dist-info/entry_points.txt
Sannidhya_102103348-0.2.0.dist-info/top_level.txt
Sannidhya_102103348-0.2.0.dist-info/RECORD
